__init__.py
nonebot_plugin_ddns/__init__.py
nonebot_plugin_ddns/ddns/__init__.py
nonebot_plugin_ddns/ddns/base.py
nonebot_plugin_ddns/ddns/dnspod.py
nonebot_plugin_ddns/ddns/utlis.py
nonebot_plugin_ddns/web/__init__.py
nonebot_plugin_ddns-0.1.0.dist-info/LICENSE.txt
nonebot_plugin_ddns-0.1.0.dist-info/METADATA
nonebot_plugin_ddns-0.1.0.dist-info/WHEEL
nonebot_plugin_ddns-0.1.0.dist-info/top_level.txt
nonebot_plugin_ddns-0.1.0.dist-info/RECORD
