Metadata-Version: 2.1
Name: nonebot-plugin-ddns
Version: 0.1.0
Author-email: alnthy <2580424155@qq.com>
License: GPL-3.0
Requires-Python: >=3.11
License-File: LICENSE.txt
Requires-Dist: nonebot2 >=2.0.1
Requires-Dist: httpx >=0.24.1
Requires-Dist: fastapi >=0.101.1
Requires-Dist: tencentcloud-sdk-python-dnspod >=3.0.965
Requires-Dist: uvicorn >=0.23.2
